{
  "data": {
    "data": {
      "items": [
        {
          "id": "5448fee04bdc2dbc018b4567",
          "name": "Bottle of water (0.6L)",
          "shortName": "Water",
          "avg24hPrice": 14864,
          "lastLowPrice": 13333,
          "changeLast48h": -866,
          "changeLast48hPercent": -5.51,
          "updated": "2025-06-21T19:09:50.000Z",
          "sellFor": [
            {
              "source": "therapist",
              "price": 1543,
              "currency": "RUB",
              "priceRUB": 1543
            },
            {
              "source": "fence",
              "price": 980,
              "currency": "RUB",
              "priceRUB": 980
            },
            {
              "source": "jaeger",
              "price": 1470,
              "currency": "RUB",
              "priceRUB": 1470
            },
            {
              "source": "fleaMarket",
              "price": 13333,
              "currency": "RUB",
              "priceRUB": 13333
            }
          ],
          "iconLink": "https://assets.tarkov.dev/5448fee04bdc2dbc018b4567-icon.webp",
          "wikiLink": "https://escapefromtarkov.fandom.com/wiki/Bottle_of_water_(0.6L)"
        },
        {
          "id": "544fb3f34bdc2d03748b456a",
          "name": "Morphine injector",
          "shortName": "Morphine",
          "avg24hPrice": 20164,
          "lastLowPrice": 16999,
          "changeLast48h": -88,
          "changeLast48hPercent": -0.43,
          "updated": "2025-06-21T19:35:30.000Z",
          "sellFor": [
            {
              "source": "prapor",
              "price": 12652,
              "currency": "RUB",
              "priceRUB": 12652
            },
            {
              "source": "therapist",
              "price": 15942,
              "currency": "RUB",
              "priceRUB": 15942
            },
            {
              "source": "fence",
              "price": 10122,
              "currency": "RUB",
              "priceRUB": 10122
            },
            {
              "source": "jaeger",
              "price": 15183,
              "currency": "RUB",
              "priceRUB": 15183
            },
            {
              "source": "fleaMarket",
              "price": 16999,
              "currency": "RUB",
              "priceRUB": 16999
            }
          ],
          "iconLink": "https://assets.tarkov.dev/544fb3f34bdc2d03748b456a-icon.webp",
          "wikiLink": "https://escapefromtarkov.fandom.com/wiki/Morphine_injector"
        },
        {
          "id": "5733279d245977289b77ec24",
          "name": "Car battery",
          "shortName": "Car battery",
          "avg24hPrice": 38771,
          "lastLowPrice": 38770,
          "changeLast48h": 0,
          "changeLast48hPercent": 0,
          "updated": "2025-06-21T19:11:12.000Z",
          "sellFor": [
            {
              "source": "therapist",
              "price": 38784,
              "currency": "RUB",
              "priceRUB": 38784
            },
            {
              "source": "fence",
              "price": 24625,
              "currency": "RUB",
              "priceRUB": 24625
            },
            {
              "source": "peacekeeper",
              "price": 235,
              "currency": "USD",
              "priceRUB": 27703
            },
            {
              "source": "mechanic",
              "price": 34475,
              "currency": "RUB",
              "priceRUB": 34475
            },
            {
              "source": "jaeger",
              "price": 36937,
              "currency": "RUB",
              "priceRUB": 36937
            },
            {
              "source": "fleaMarket",
              "price": 38770,
              "currency": "RUB",
              "priceRUB": 38770
            }
          ],
          "iconLink": "https://assets.tarkov.dev/5733279d245977289b77ec24-icon.webp",
          "wikiLink": "https://escapefromtarkov.fandom.com/wiki/Car_battery"
        },
        {
          "id": "5734779624597737e04bf329",
          "name": "CPU fan",
          "shortName": "CPU fan",
          "avg24hPrice": 4251,
          "lastLowPrice": 3500,
          "changeLast48h": -644,
          "changeLast48hPercent": -13.16,
          "updated": "2025-06-21T19:04:55.000Z",
          "sellFor": [
            {
              "source": "therapist",
              "price": 2942,
              "currency": "RUB",
              "priceRUB": 2942
            },
            {
              "source": "fence",
              "price": 1868,
              "currency": "RUB",
              "priceRUB": 1868
            },
            {
              "source": "skier",
              "price": 2288,
              "currency": "RUB",
              "priceRUB": 2288
            },
            {
              "source": "peacekeeper",
              "price": 18,
              "currency": "USD",
              "priceRUB": 2101
            },
            {
              "source": "mechanic",
              "price": 2615,
              "currency": "RUB",
              "priceRUB": 2615
            },
            {
              "source": "fleaMarket",
              "price": 3500,
              "currency": "RUB",
              "priceRUB": 3500
            }
          ],
          "iconLink": "https://assets.tarkov.dev/5734779624597737e04bf329-icon.webp",
          "wikiLink": "https://escapefromtarkov.fandom.com/wiki/CPU_fan"
        },
        {
          "id": "573477e124597737dd42e191",
          "name": "PC CPU",
          "shortName": "CPU",
          "avg24hPrice": 14642,
          "lastLowPrice": 11500,
          "changeLast48h": -1780,
          "changeLast48hPercent": -10.84,
          "updated": "2025-06-21T19:58:00.000Z",
          "sellFor": [
            {
              "source": "therapist",
              "price": 8765,
              "currency": "RUB",
              "priceRUB": 8765
            },
            {
              "source": "fence",
              "price": 5565,
              "currency": "RUB",
              "priceRUB": 5565
            },
            {
              "source": "skier",
              "price": 6817,
              "currency": "RUB",
              "priceRUB": 6817
            },
            {
              "source": "peacekeeper",
              "price": 53,
              "currency": "USD",
              "priceRUB": 6261
            },
            {
              "source": "mechanic",
              "price": 7791,
              "currency": "RUB",
              "priceRUB": 7791
            },
            {
              "source": "fleaMarket",
              "price": 11500,
              "currency": "RUB",
              "priceRUB": 11500
            }
          ],
          "iconLink": "https://assets.tarkov.dev/573477e124597737dd42e191-icon.webp",
          "wikiLink": "https://escapefromtarkov.fandom.com/wiki/PC_CPU"
        },
        {
          "id": "57347ca924597744596b4e71",
          "name": "Graphics card",
          "shortName": "GPU",
          "avg24hPrice": 185270,
          "lastLowPrice": 169999,
          "changeLast48h": 4107,
          "changeLast48hPercent": 2.27,
          "updated": "2025-06-21T19:19:09.000Z",
          "sellFor": [
            {
              "source": "therapist",
              "price": 124740,
              "currency": "RUB",
              "priceRUB": 124740
            },
            {
              "source": "fence",
              "price": 79200,
              "currency": "RUB",
              "priceRUB": 79200
            },
            {
              "source": "skier",
              "price": 97020,
              "currency": "RUB",
              "priceRUB": 97020
            },
            {
              "source": "peacekeeper",
              "price": 755,
              "currency": "USD",
              "priceRUB": 89100
            },
            {
              "source": "mechanic",
              "price": 110880,
              "currency": "RUB",
              "priceRUB": 110880
            },
            {
              "source": "fleaMarket",
              "price": 169999,
              "currency": "RUB",
              "priceRUB": 169999
            }
          ],
          "iconLink": "https://assets.tarkov.dev/57347ca924597744596b4e71-icon.webp",
          "wikiLink": "https://escapefromtarkov.fandom.com/wiki/Graphics_card"
        },
        {
          "id": "57505f6224597709a92585a9",
          "name": "Alyonka chocolate bar",
          "shortName": "Alyonka",
          "avg24hPrice": 36822,
          "lastLowPrice": 29888,
          "changeLast48h": 121,
          "changeLast48hPercent": 0.33,
          "updated": "2025-06-21T19:17:59.000Z",
          "sellFor": [
            {
              "source": "therapist",
              "price": 6604,
              "currency": "RUB",
              "priceRUB": 6604
            },
            {
              "source": "fence",
              "price": 4193,
              "currency": "RUB",
              "priceRUB": 4193
            },
            {
              "source": "jaeger",
              "price": 6289,
              "currency": "RUB",
              "priceRUB": 6289
            },
            {
              "source": "fleaMarket",
              "price": 29888,
              "currency": "RUB",
              "priceRUB": 29888
            }
          ],
          "iconLink": "https://assets.tarkov.dev/57505f6224597709a92585a9-icon.webp",
          "wikiLink": "https://escapefromtarkov.fandom.com/wiki/Alyonka_chocolate_bar"
        },
        {
          "id": "57513f07245977207e26a311",
          "name": "Pack of apple juice",
          "shortName": "Apple",
          "avg24hPrice": 14018,
          "lastLowPrice": 7600,
          "changeLast48h": -514,
          "changeLast48hPercent": -3.54,
          "updated": "2025-06-21T19:24:51.000Z",
          "sellFor": [
            {
              "source": "therapist",
              "price": 2155,
              "currency": "RUB",
              "priceRUB": 2155
            },
            {
              "source": "fence",
              "price": 1368,
              "currency": "RUB",
              "priceRUB": 1368
            },
            {
              "source": "jaeger",
              "price": 2053,
              "currency": "RUB",
              "priceRUB": 2053
            },
            {
              "source": "fleaMarket",
              "price": 7600,
              "currency": "RUB",
              "priceRUB": 7600
            }
          ],
          "iconLink": "https://assets.tarkov.dev/57513f07245977207e26a311-icon.webp",
          "wikiLink": "https://escapefromtarkov.fandom.com/wiki/Pack_of_apple_juice"
        },
        {
          "id": "5751435d24597720a27126d1",
          "name": "Can of Max Energy energy drink",
          "shortName": "MaxEnergy",
          "avg24hPrice": 20586,
          "lastLowPrice": 19000,
          "changeLast48h": -430,
          "changeLast48hPercent": -2.05,
          "updated": "2025-06-21T19:20:11.000Z",
          "sellFor": [
            {
              "source": "therapist",
              "price": 5628,
              "currency": "RUB",
              "priceRUB": 5628
            },
            {
              "source": "fence",
              "price": 3573,
              "currency": "RUB",
              "priceRUB": 3573
            },
            {
              "source": "jaeger",
              "price": 5360,
              "currency": "RUB",
              "priceRUB": 5360
            },
            {
              "source": "fleaMarket",
              "price": 19000,
              "currency": "RUB",
              "priceRUB": 19000
            }
          ],
          "iconLink": "https://assets.tarkov.dev/5751435d24597720a27126d1-icon.webp",
          "wikiLink": "https://escapefromtarkov.fandom.com/wiki/Can_of_Max_Energy_energy_drink"
        },
        {
          "id": "5751a89d24597722aa0e8db0",
          "name": "Golden Star balm",
          "shortName": "GoldenStar",
          "avg24hPrice": 158417,
          "lastLowPrice": 165000,
          "changeLast48h": 4443,
          "changeLast48hPercent": 2.89,
          "updated": "2025-06-21T19:57:32.000Z",
          "sellFor": [
            {
              "source": "prapor",
              "price": 14444,
              "currency": "RUB",
              "priceRUB": 14444
            },
            {
              "source": "therapist",
              "price": 18200,
              "currency": "RUB",
              "priceRUB": 18200
            },
            {
              "source": "fence",
              "price": 11555,
              "currency": "RUB",
              "priceRUB": 11555
            },
            {
              "source": "jaeger",
              "price": 17333,
              "currency": "RUB",
              "priceRUB": 17333
            },
            {
              "source": "fleaMarket",
              "price": 165000,
              "currency": "RUB",
              "priceRUB": 165000
            }
          ],
          "iconLink": "https://assets.tarkov.dev/5751a89d24597722aa0e8db0-icon.webp",
          "wikiLink": "https://escapefromtarkov.fandom.com/wiki/Golden_Star_balm"
        },
        {
          "id": "590a3b0486f7743954552bdb",
          "name": "Printed circuit board",
          "shortName": "PCB",
          "avg24hPrice": 23534,
          "lastLowPrice": 27000,
          "changeLast48h": 848,
          "changeLast48hPercent": 3.74,
          "updated": "2025-06-21T19:10:51.000Z",
          "sellFor": [
            {
              "source": "therapist",
              "price": 8031,
              "currency": "RUB",
              "priceRUB": 8031
            },
            {
              "source": "fence",
              "price": 5099,
              "currency": "RUB",
              "priceRUB": 5099
            },
            {
              "source": "skier",
              "price": 6247,
              "currency": "RUB",
              "priceRUB": 6247
            },
            {
              "source": "peacekeeper",
              "price": 49,
              "currency": "USD",
              "priceRUB": 5737
            },
            {
              "source": "mechanic",
              "price": 7139,
              "currency": "RUB",
              "priceRUB": 7139
            },
            {
              "source": "fleaMarket",
              "price": 27000,
              "currency": "RUB",
              "priceRUB": 27000
            }
          ],
          "iconLink": "https://assets.tarkov.dev/590a3b0486f7743954552bdb-icon.webp",
          "wikiLink": "https://escapefromtarkov.fandom.com/wiki/Printed_circuit_board"
        },
        {
          "id": "590c2e1186f77425357b6124",
          "name": "Toolset",
          "shortName": "Toolset",
          "avg24hPrice": 38177,
          "lastLowPrice": 27777,
          "changeLast48h": -109,
          "changeLast48hPercent": -0.28,
          "updated": "2025-06-21T19:50:26.000Z",
          "sellFor": [
            {
              "source": "prapor",
              "price": 15500,
              "currency": "RUB",
              "priceRUB": 15500
            },
            {
              "source": "therapist",
              "price": 19530,
              "currency": "RUB",
              "priceRUB": 19530
            },
            {
              "source": "fence",
              "price": 12400,
              "currency": "RUB",
              "priceRUB": 12400
            },
            {
              "source": "mechanic",
              "price": 17360,
              "currency": "RUB",
              "priceRUB": 17360
            },
            {
              "source": "fleaMarket",
              "price": 27777,
              "currency": "RUB",
              "priceRUB": 27777
            }
          ],
          "iconLink": "https://assets.tarkov.dev/590c2e1186f77425357b6124-icon.webp",
          "wikiLink": "https://escapefromtarkov.fandom.com/wiki/Toolset"
        },
        {
          "id": "590c5a7286f7747884343aea",
          "name": "Gunpowder \"Kite\"",
          "shortName": "Kite",
          "avg24hPrice": 26057,
          "lastLowPrice": 18500,
          "changeLast48h": -2408,
          "changeLast48hPercent": -8.46,
          "updated": "2025-06-21T19:54:45.000Z",
          "sellFor": [
            {
              "source": "prapor",
              "price": 7000,
              "currency": "RUB",
              "priceRUB": 7000
            },
            {
              "source": "therapist",
              "price": 8820,
              "currency": "RUB",
              "priceRUB": 8820
            },
            {
              "source": "fence",
              "price": 5600,
              "currency": "RUB",
              "priceRUB": 5600
            },
            {
              "source": "skier",
              "price": 6860,
              "currency": "RUB",
              "priceRUB": 6860
            },
            {
              "source": "fleaMarket",
              "price": 18500,
              "currency": "RUB",
              "priceRUB": 18500
            }
          ],
          "iconLink": "https://assets.tarkov.dev/590c5a7286f7747884343aea-icon.webp",
          "wikiLink": "https://escapefromtarkov.fandom.com/wiki/Gunpowder_%22Kite%22"
        },
        {
          "id": "590c639286f774151567fa95",
          "name": "Tech manual",
          "shortName": "Manual",
          "avg24hPrice": 14797,
          "lastLowPrice": 11100,
          "changeLast48h": -235,
          "changeLast48hPercent": -1.57,
          "updated": "2025-06-21T19:00:11.000Z",
          "sellFor": [
            {
              "source": "fence",
              "price": 9560,
              "currency": "RUB",
              "priceRUB": 9560
            },
            {
              "source": "peacekeeper",
              "price": 91,
              "currency": "USD",
              "priceRUB": 10755
            },
            {
              "source": "fleaMarket",
              "price": 11100,
              "currency": "RUB",
              "priceRUB": 11100
            }
          ],
          "iconLink": "https://assets.tarkov.dev/590c639286f774151567fa95-icon.webp",
          "wikiLink": "https://escapefromtarkov.fandom.com/wiki/Tech_manual"
        },
        {
          "id": "59e3577886f774176a362503",
          "name": "Pack of sugar",
          "shortName": "Sugar",
          "avg24hPrice": 67898,
          "lastLowPrice": 55555,
          "changeLast48h": -3352,
          "changeLast48hPercent": -4.71,
          "updated": "2025-06-21T19:36:00.000Z",
          "sellFor": [
            {
              "source": "therapist",
              "price": 13538,
              "currency": "RUB",
              "priceRUB": 13538
            },
            {
              "source": "fence",
              "price": 8595,
              "currency": "RUB",
              "priceRUB": 8595
            },
            {
              "source": "jaeger",
              "price": 12893,
              "currency": "RUB",
              "priceRUB": 12893
            },
            {
              "source": "fleaMarket",
              "price": 55555,
              "currency": "RUB",
              "priceRUB": 55555
            }
          ],
          "iconLink": "https://assets.tarkov.dev/59e3577886f774176a362503-icon.webp",
          "wikiLink": "https://escapefromtarkov.fandom.com/wiki/Pack_of_sugar"
        },
        {
          "id": "59e3606886f77417674759a5",
          "name": "Bottle of saline solution",
          "shortName": "NaCl",
          "avg24hPrice": 26513,
          "lastLowPrice": 21777,
          "changeLast48h": 1232,
          "changeLast48hPercent": 4.87,
          "updated": "2025-06-21T19:06:32.000Z",
          "sellFor": [
            {
              "source": "therapist",
              "price": 5360,
              "currency": "RUB",
              "priceRUB": 5360
            },
            {
              "source": "fence",
              "price": 3403,
              "currency": "RUB",
              "priceRUB": 3403
            },
            {
              "source": "jaeger",
              "price": 5104,
              "currency": "RUB",
              "priceRUB": 5104
            },
            {
              "source": "fleaMarket",
              "price": 21777,
              "currency": "RUB",
              "priceRUB": 21777
            }
          ],
          "iconLink": "https://assets.tarkov.dev/59e3606886f77417674759a5-icon.webp",
          "wikiLink": "https://escapefromtarkov.fandom.com/wiki/Bottle_of_saline_solution"
        },
        {
          "id": "59e361e886f774176c10a2a5",
          "name": "Bottle of hydrogen peroxide",
          "shortName": "H2O2",
          "avg24hPrice": 36282,
          "lastLowPrice": 22222,
          "changeLast48h": -11780,
          "changeLast48hPercent": -24.51,
          "updated": "2025-06-21T19:05:11.000Z",
          "sellFor": [
            {
              "source": "therapist",
              "price": 7665,
              "currency": "RUB",
              "priceRUB": 7665
            },
            {
              "source": "fence",
              "price": 4867,
              "currency": "RUB",
              "priceRUB": 4867
            },
            {
              "source": "jaeger",
              "price": 7300,
              "currency": "RUB",
              "priceRUB": 7300
            },
            {
              "source": "fleaMarket",
              "price": 22222,
              "currency": "RUB",
              "priceRUB": 22222
            }
          ],
          "iconLink": "https://assets.tarkov.dev/59e361e886f774176c10a2a5-icon.webp",
          "wikiLink": "https://escapefromtarkov.fandom.com/wiki/Bottle_of_hydrogen_peroxide"
        },
        {
          "id": "59e3647686f774176a362507",
          "name": "Wooden clock",
          "shortName": "Clock",
          "avg24hPrice": 69958,
          "lastLowPrice": 64000,
          "changeLast48h": -20191,
          "changeLast48hPercent": -22.4,
          "updated": "2025-06-21T19:38:56.000Z",
          "sellFor": [
            {
              "source": "therapist",
              "price": 52489,
              "currency": "RUB",
              "priceRUB": 52489
            },
            {
              "source": "fence",
              "price": 33326,
              "currency": "RUB",
              "priceRUB": 33326
            },
            {
              "source": "skier",
              "price": 40824,
              "currency": "RUB",
              "priceRUB": 40824
            },
            {
              "source": "peacekeeper",
              "price": 318,
              "currency": "USD",
              "priceRUB": 37492
            },
            {
              "source": "fleaMarket",
              "price": 64000,
              "currency": "RUB",
              "priceRUB": 64000
            }
          ],
          "iconLink": "https://assets.tarkov.dev/59e3647686f774176a362507-icon.webp",
          "wikiLink": "https://escapefromtarkov.fandom.com/wiki/Wooden_clock"
        },
        {
          "id": "59faf7ca86f7740dbe19f6c2",
          "name": "Roler Submariner gold wrist watch",
          "shortName": "Roler",
          "avg24hPrice": 62856,
          "lastLowPrice": 58888,
          "changeLast48h": -3140,
          "changeLast48hPercent": -4.76,
          "updated": "2025-06-21T19:26:00.000Z",
          "sellFor": [
            {
              "source": "therapist",
              "price": 44760,
              "currency": "RUB",
              "priceRUB": 44760
            },
            {
              "source": "fence",
              "price": 28419,
              "currency": "RUB",
              "priceRUB": 28419
            },
            {
              "source": "skier",
              "price": 34814,
              "currency": "RUB",
              "priceRUB": 34814
            },
            {
              "source": "peacekeeper",
              "price": 271,
              "currency": "USD",
              "priceRUB": 31972
            },
            {
              "source": "fleaMarket",
              "price": 58888,
              "currency": "RUB",
              "priceRUB": 58888
            }
          ],
          "iconLink": "https://assets.tarkov.dev/59faf7ca86f7740dbe19f6c2-icon.webp",
          "wikiLink": "https://escapefromtarkov.fandom.com/wiki/Roler_Submariner_gold_wrist_watch"
        },
        {
          "id": "59fafb5d86f774067a6f2084",
          "name": "Propane tank (5L)",
          "shortName": "Propane",
          "avg24hPrice": 37688,
          "lastLowPrice": 20000,
          "changeLast48h": -6704,
          "changeLast48hPercent": -15.1,
          "updated": "2025-06-21T19:24:02.000Z",
          "sellFor": [
            {
              "source": "therapist",
              "price": 7966,
              "currency": "RUB",
              "priceRUB": 7966
            },
            {
              "source": "fence",
              "price": 5058,
              "currency": "RUB",
              "priceRUB": 5058
            },
            {
              "source": "jaeger",
              "price": 7587,
              "currency": "RUB",
              "priceRUB": 7587
            },
            {
              "source": "fleaMarket",
              "price": 20000,
              "currency": "RUB",
              "priceRUB": 20000
            }
          ],
          "iconLink": "https://assets.tarkov.dev/59fafb5d86f774067a6f2084-icon.webp",
          "wikiLink": "https://escapefromtarkov.fandom.com/wiki/Propane_tank_(5L)"
        },
        {
          "id": "5af04b6486f774195a3ebb49",
          "name": "Pliers Elite",
          "shortName": "Elite",
          "avg24hPrice": 19196,
          "lastLowPrice": 14444,
          "changeLast48h": -827,
          "changeLast48hPercent": -4.13,
          "updated": "2025-06-21T19:54:55.000Z",
          "sellFor": [
            {
              "source": "prapor",
              "price": 14500,
              "currency": "RUB",
              "priceRUB": 14500
            },
            {
              "source": "therapist",
              "price": 18270,
              "currency": "RUB",
              "priceRUB": 18270
            },
            {
              "source": "fence",
              "price": 11600,
              "currency": "RUB",
              "priceRUB": 11600
            },
            {
              "source": "mechanic",
              "price": 16240,
              "currency": "RUB",
              "priceRUB": 16240
            },
            {
              "source": "fleaMarket",
              "price": 14444,
              "currency": "RUB",
              "priceRUB": 14444
            }
          ],
          "iconLink": "https://assets.tarkov.dev/5af04b6486f774195a3ebb49-icon.webp",
          "wikiLink": "https://escapefromtarkov.fandom.com/wiki/Pliers_Elite"
        },
        {
          "id": "5af0548586f7743a532b7e99",
          "name": "Ibuprofen painkillers",
          "shortName": "Ibuprofen",
          "avg24hPrice": 105037,
          "lastLowPrice": 82700,
          "changeLast48h": -2196,
          "changeLast48hPercent": -2.05,
          "updated": "2025-06-21T19:43:38.000Z",
          "sellFor": [
            {
              "source": "prapor",
              "price": 12617,
              "currency": "RUB",
              "priceRUB": 12617
            },
            {
              "source": "therapist",
              "price": 15898,
              "currency": "RUB",
              "priceRUB": 15898
            },
            {
              "source": "fence",
              "price": 10094,
              "currency": "RUB",
              "priceRUB": 10094
            },
            {
              "source": "jaeger",
              "price": 15141,
              "currency": "RUB",
              "priceRUB": 15141
            },
            {
              "source": "fleaMarket",
              "price": 82700,
              "currency": "RUB",
              "priceRUB": 82700
            }
          ],
          "iconLink": "https://assets.tarkov.dev/5af0548586f7743a532b7e99-icon.webp",
          "wikiLink": "https://escapefromtarkov.fandom.com/wiki/Ibuprofen_painkillers"
        },
        {
          "id": "5bc9be8fd4351e00334cae6e",
          "name": "42 Signature Blend English Tea",
          "shortName": "42",
          "avg24hPrice": 20469,
          "lastLowPrice": 17000,
          "changeLast48h": -2315,
          "changeLast48hPercent": -10.16,
          "updated": "2025-06-21T19:06:47.000Z",
          "sellFor": [
            {
              "source": "prapor",
              "price": 13877,
              "currency": "RUB",
              "priceRUB": 13877
            },
            {
              "source": "therapist",
              "price": 17485,
              "currency": "RUB",
              "priceRUB": 17485
            },
            {
              "source": "fence",
              "price": 11101,
              "currency": "RUB",
              "priceRUB": 11101
            },
            {
              "source": "skier",
              "price": 13599,
              "currency": "RUB",
              "priceRUB": 13599
            },
            {
              "source": "fleaMarket",
              "price": 17000,
              "currency": "RUB",
              "priceRUB": 17000
            }
          ],
          "iconLink": "https://assets.tarkov.dev/5bc9be8fd4351e00334cae6e-icon.webp",
          "wikiLink": "https://escapefromtarkov.fandom.com/wiki/42_Signature_Blend_English_Tea"
        },
        {
          "id": "5c05300686f7746dce784e5d",
          "name": "VPX Flash Storage Module",
          "shortName": "VPX",
          "avg24hPrice": 101046,
          "lastLowPrice": 96666,
          "changeLast48h": -6331,
          "changeLast48hPercent": -5.9,
          "updated": "2025-06-21T19:35:37.000Z",
          "sellFor": [
            {
              "source": "therapist",
              "price": 96012,
              "currency": "RUB",
              "priceRUB": 96012
            },
            {
              "source": "fence",
              "price": 60960,
              "currency": "RUB",
              "priceRUB": 60960
            },
            {
              "source": "skier",
              "price": 74676,
              "currency": "RUB",
              "priceRUB": 74676
            },
            {
              "source": "peacekeeper",
              "price": 581,
              "currency": "USD",
              "priceRUB": 68580
            },
            {
              "source": "mechanic",
              "price": 85344,
              "currency": "RUB",
              "priceRUB": 85344
            },
            {
              "source": "fleaMarket",
              "price": 96666,
              "currency": "RUB",
              "priceRUB": 96666
            }
          ],
          "iconLink": "https://assets.tarkov.dev/5c05300686f7746dce784e5d-icon.webp",
          "wikiLink": "https://escapefromtarkov.fandom.com/wiki/VPX_Flash_Storage_Module"
        },
        {
          "id": "5c05308086f7746b2101e90b",
          "name": "Virtex programmable processor",
          "shortName": "Virtex",
          "avg24hPrice": 172739,
          "lastLowPrice": 140000,
          "changeLast48h": 36620,
          "changeLast48hPercent": 26.9,
          "updated": "2025-06-21T19:22:55.000Z",
          "sellFor": [
            {
              "source": "therapist",
              "price": 75600,
              "currency": "RUB",
              "priceRUB": 75600
            },
            {
              "source": "fence",
              "price": 48000,
              "currency": "RUB",
              "priceRUB": 48000
            },
            {
              "source": "skier",
              "price": 58800,
              "currency": "RUB",
              "priceRUB": 58800
            },
            {
              "source": "peacekeeper",
              "price": 458,
              "currency": "USD",
              "priceRUB": 54000
            },
            {
              "source": "mechanic",
              "price": 67200,
              "currency": "RUB",
              "priceRUB": 67200
            },
            {
              "source": "fleaMarket",
              "price": 140000,
              "currency": "RUB",
              "priceRUB": 140000
            }
          ],
          "iconLink": "https://assets.tarkov.dev/5c05308086f7746b2101e90b-icon.webp",
          "wikiLink": "https://escapefromtarkov.fandom.com/wiki/Virtex_programmable_processor"
        },
        {
          "id": "5c0530ee86f774697952d952",
          "name": "LEDX Skin Transilluminator",
          "shortName": "LEDX",
          "avg24hPrice": 695435,
          "lastLowPrice": 699000,
          "changeLast48h": -9836,
          "changeLast48hPercent": -1.39,
          "updated": "2025-06-21T19:07:19.000Z",
          "sellFor": [
            {
              "source": "therapist",
              "price": 611100,
              "currency": "RUB",
              "priceRUB": 611100
            },
            {
              "source": "fence",
              "price": 388000,
              "currency": "RUB",
              "priceRUB": 388000
            },
            {
              "source": "jaeger",
              "price": 582000,
              "currency": "RUB",
              "priceRUB": 582000
            },
            {
              "source": "fleaMarket",
              "price": 699000,
              "currency": "RUB",
              "priceRUB": 699000
            }
          ],
          "iconLink": "https://assets.tarkov.dev/5c0530ee86f774697952d952-icon.webp",
          "wikiLink": "https://escapefromtarkov.fandom.com/wiki/LEDX_Skin_Transilluminator"
        },
        {
          "id": "5c0e530286f7747fa1419862",
          "name": "Propital regenerative stimulant injector",
          "shortName": "Propital",
          "avg24hPrice": 41022,
          "lastLowPrice": 39999,
          "changeLast48h": -2034,
          "changeLast48hPercent": -4.72,
          "updated": "2025-06-21T19:32:13.000Z",
          "sellFor": [
            {
              "source": "prapor",
              "price": 10530,
              "currency": "RUB",
              "priceRUB": 10530
            },
            {
              "source": "therapist",
              "price": 13267,
              "currency": "RUB",
              "priceRUB": 13267
            },
            {
              "source": "fence",
              "price": 8424,
              "currency": "RUB",
              "priceRUB": 8424
            },
            {
              "source": "skier",
              "price": 10319,
              "currency": "RUB",
              "priceRUB": 10319
            },
            {
              "source": "jaeger",
              "price": 12636,
              "currency": "RUB",
              "priceRUB": 12636
            },
            {
              "source": "fleaMarket",
              "price": 39999,
              "currency": "RUB",
              "priceRUB": 39999
            }
          ],
          "iconLink": "https://assets.tarkov.dev/5c0e530286f7747fa1419862-icon.webp",
          "wikiLink": "https://escapefromtarkov.fandom.com/wiki/Propital_regenerative_stimulant_injector"
        },
        {
          "id": "5c0e531286f7747fa54205c2",
          "name": "SJ1 TGLabs combat stimulant injector",
          "shortName": "SJ1",
          "avg24hPrice": 55651,
          "lastLowPrice": 44999,
          "changeLast48h": -8956,
          "changeLast48hPercent": -13.86,
          "updated": "2025-06-21T19:49:48.000Z",
          "sellFor": [
            {
              "source": "prapor",
              "price": 17946,
              "currency": "RUB",
              "priceRUB": 17946
            },
            {
              "source": "therapist",
              "price": 22612,
              "currency": "RUB",
              "priceRUB": 22612
            },
            {
              "source": "fence",
              "price": 14357,
              "currency": "RUB",
              "priceRUB": 14357
            },
            {
              "source": "skier",
              "price": 17587,
              "currency": "RUB",
              "priceRUB": 17587
            },
            {
              "source": "jaeger",
              "price": 21535,
              "currency": "RUB",
              "priceRUB": 21535
            },
            {
              "source": "fleaMarket",
              "price": 44999,
              "currency": "RUB",
              "priceRUB": 44999
            }
          ],
          "iconLink": "https://assets.tarkov.dev/5c0e531286f7747fa54205c2-icon.webp",
          "wikiLink": "https://escapefromtarkov.fandom.com/wiki/SJ1_TGLabs_combat_stimulant_injector"
        },
        {
          "id": "5c0e533786f7747fa23f4d47",
          "name": "Zagustin hemostatic drug injector",
          "shortName": "Zagustin",
          "avg24hPrice": 47422,
          "lastLowPrice": 45000,
          "changeLast48h": -1,
          "changeLast48hPercent": 0,
          "updated": "2025-06-21T19:04:20.000Z",
          "sellFor": [
            {
              "source": "prapor",
              "price": 16770,
              "currency": "RUB",
              "priceRUB": 16770
            },
            {
              "source": "therapist",
              "price": 21130,
              "currency": "RUB",
              "priceRUB": 21130
            },
            {
              "source": "fence",
              "price": 13416,
              "currency": "RUB",
              "priceRUB": 13416
            },
            {
              "source": "skier",
              "price": 16434,
              "currency": "RUB",
              "priceRUB": 16434
            },
            {
              "source": "jaeger",
              "price": 20124,
              "currency": "RUB",
              "priceRUB": 20124
            },
            {
              "source": "fleaMarket",
              "price": 45000,
              "currency": "RUB",
              "priceRUB": 45000
            }
          ],
          "iconLink": "https://assets.tarkov.dev/5c0e533786f7747fa23f4d47-icon.webp",
          "wikiLink": "https://escapefromtarkov.fandom.com/wiki/Zagustin_hemostatic_drug_injector"
        },
        {
          "id": "5c12620d86f7743f8b198b72",
          "name": "Tetriz portable game console",
          "shortName": "Tetriz",
          "avg24hPrice": 325031,
          "lastLowPrice": 287000,
          "changeLast48h": -1675,
          "changeLast48hPercent": -0.51,
          "updated": "2025-06-21T19:47:58.000Z",
          "sellFor": [
            {
              "source": "therapist",
              "price": 75600,
              "currency": "RUB",
              "priceRUB": 75600
            },
            {
              "source": "fence",
              "price": 48000,
              "currency": "RUB",
              "priceRUB": 48000
            },
            {
              "source": "skier",
              "price": 58800,
              "currency": "RUB",
              "priceRUB": 58800
            },
            {
              "source": "peacekeeper",
              "price": 458,
              "currency": "USD",
              "priceRUB": 54000
            },
            {
              "source": "mechanic",
              "price": 67200,
              "currency": "RUB",
              "priceRUB": 67200
            },
            {
              "source": "fleaMarket",
              "price": 287000,
              "currency": "RUB",
              "priceRUB": 287000
            }
          ],
          "iconLink": "https://assets.tarkov.dev/5c12620d86f7743f8b198b72-icon.webp",
          "wikiLink": "https://escapefromtarkov.fandom.com/wiki/Tetriz_portable_game_console"
        },
        {
          "id": "5d0376a486f7747d8050965c",
          "name": "Military circuit board",
          "shortName": "MCB",
          "avg24hPrice": 74117,
          "lastLowPrice": 125554,
          "changeLast48h": -3795,
          "changeLast48hPercent": -4.87,
          "updated": "2025-06-21T19:23:59.000Z",
          "sellFor": [
            {
              "source": "therapist",
              "price": 25200,
              "currency": "RUB",
              "priceRUB": 25200
            },
            {
              "source": "fence",
              "price": 16000,
              "currency": "RUB",
              "priceRUB": 16000
            },
            {
              "source": "skier",
              "price": 19600,
              "currency": "RUB",
              "priceRUB": 19600
            },
            {
              "source": "peacekeeper",
              "price": 153,
              "currency": "USD",
              "priceRUB": 18000
            },
            {
              "source": "mechanic",
              "price": 22400,
              "currency": "RUB",
              "priceRUB": 22400
            },
            {
              "source": "fleaMarket",
              "price": 125554,
              "currency": "RUB",
              "priceRUB": 125554
            }
          ],
          "iconLink": "https://assets.tarkov.dev/5d0376a486f7747d8050965c-icon.webp",
          "wikiLink": "https://escapefromtarkov.fandom.com/wiki/Military_circuit_board"
        },
        {
          "id": "5d0377ce86f774186372f689",
          "name": "Iridium military thermal vision module",
          "shortName": "Iridium",
          "avg24hPrice": 80372,
          "lastLowPrice": 77777,
          "changeLast48h": -4842,
          "changeLast48hPercent": -5.68,
          "updated": "2025-06-21T19:33:36.000Z",
          "sellFor": [
            {
              "source": "therapist",
              "price": 51156,
              "currency": "RUB",
              "priceRUB": 51156
            },
            {
              "source": "fence",
              "price": 32480,
              "currency": "RUB",
              "priceRUB": 32480
            },
            {
              "source": "skier",
              "price": 39788,
              "currency": "RUB",
              "priceRUB": 39788
            },
            {
              "source": "peacekeeper",
              "price": 310,
              "currency": "USD",
              "priceRUB": 36540
            },
            {
              "source": "mechanic",
              "price": 45472,
              "currency": "RUB",
              "priceRUB": 45472
            },
            {
              "source": "fleaMarket",
              "price": 77777,
              "currency": "RUB",
              "priceRUB": 77777
            }
          ],
          "iconLink": "https://assets.tarkov.dev/5d0377ce86f774186372f689-icon.webp",
          "wikiLink": "https://escapefromtarkov.fandom.com/wiki/Iridium_military_thermal_vision_module"
        },
        {
          "id": "5d0378d486f77420421a5ff4",
          "name": "Military power filter",
          "shortName": "PFilter",
          "avg24hPrice": 45109,
          "lastLowPrice": 36666,
          "changeLast48h": 2474,
          "changeLast48hPercent": 5.8,
          "updated": "2025-06-21T19:35:11.000Z",
          "sellFor": [
            {
              "source": "therapist",
              "price": 34650,
              "currency": "RUB",
              "priceRUB": 34650
            },
            {
              "source": "fence",
              "price": 22000,
              "currency": "RUB",
              "priceRUB": 22000
            },
            {
              "source": "skier",
              "price": 26950,
              "currency": "RUB",
              "priceRUB": 26950
            },
            {
              "source": "peacekeeper",
              "price": 210,
              "currency": "USD",
              "priceRUB": 24750
            },
            {
              "source": "mechanic",
              "price": 30800,
              "currency": "RUB",
              "priceRUB": 30800
            },
            {
              "source": "fleaMarket",
              "price": 36666,
              "currency": "RUB",
              "priceRUB": 36666
            }
          ],
          "iconLink": "https://assets.tarkov.dev/5d0378d486f77420421a5ff4-icon.webp",
          "wikiLink": "https://escapefromtarkov.fandom.com/wiki/Military_power_filter"
        },
        {
          "id": "5d1b2ffd86f77425243e8d17",
          "name": "NIXXOR lens",
          "shortName": "NIXXOR",
          "avg24hPrice": 19876,
          "lastLowPrice": 15000,
          "changeLast48h": 130,
          "changeLast48hPercent": 0.66,
          "updated": "2025-06-21T19:10:41.000Z",
          "sellFor": [
            {
              "source": "therapist",
              "price": 15939,
              "currency": "RUB",
              "priceRUB": 15939
            },
            {
              "source": "fence",
              "price": 10120,
              "currency": "RUB",
              "priceRUB": 10120
            },
            {
              "source": "skier",
              "price": 12397,
              "currency": "RUB",
              "priceRUB": 12397
            },
            {
              "source": "peacekeeper",
              "price": 96,
              "currency": "USD",
              "priceRUB": 11385
            },
            {
              "source": "mechanic",
              "price": 14168,
              "currency": "RUB",
              "priceRUB": 14168
            },
            {
              "source": "fleaMarket",
              "price": 15000,
              "currency": "RUB",
              "priceRUB": 15000
            }
          ],
          "iconLink": "https://assets.tarkov.dev/5d1b2ffd86f77425243e8d17-icon.webp",
          "wikiLink": "https://escapefromtarkov.fandom.com/wiki/NIXXOR_lens"
        },
        {
          "id": "5d1b33a686f7742523398398",
          "name": "Canister with purified water",
          "shortName": "Superwater",
          "avg24hPrice": 77483,
          "lastLowPrice": 78111,
          "changeLast48h": -3002,
          "changeLast48hPercent": -3.73,
          "updated": "2025-06-21T19:58:57.000Z",
          "sellFor": [
            {
              "source": "therapist",
              "price": 31500,
              "currency": "RUB",
              "priceRUB": 31500
            },
            {
              "source": "fence",
              "price": 20000,
              "currency": "RUB",
              "priceRUB": 20000
            },
            {
              "source": "jaeger",
              "price": 30000,
              "currency": "RUB",
              "priceRUB": 30000
            },
            {
              "source": "fleaMarket",
              "price": 78111,
              "currency": "RUB",
              "priceRUB": 78111
            }
          ],
          "iconLink": "https://assets.tarkov.dev/5d1b33a686f7742523398398-icon.webp",
          "wikiLink": "https://escapefromtarkov.fandom.com/wiki/Canister_with_purified_water"
        },
        {
          "id": "5d1b376e86f774252519444e",
          "name": "Bottle of Fierce Hatchling moonshine",
          "shortName": "Moonshine",
          "avg24hPrice": 233614,
          "lastLowPrice": 230000,
          "changeLast48h": 1719,
          "changeLast48hPercent": 0.74,
          "updated": "2025-06-21T19:05:56.000Z",
          "sellFor": [
            {
              "source": "prapor",
              "price": 100000,
              "currency": "RUB",
              "priceRUB": 100000
            },
            {
              "source": "therapist",
              "price": 126000,
              "currency": "RUB",
              "priceRUB": 126000
            },
            {
              "source": "fence",
              "price": 80000,
              "currency": "RUB",
              "priceRUB": 80000
            },
            {
              "source": "jaeger",
              "price": 120000,
              "currency": "RUB",
              "priceRUB": 120000
            },
            {
              "source": "fleaMarket",
              "price": 230000,
              "currency": "RUB",
              "priceRUB": 230000
            }
          ],
          "iconLink": "https://assets.tarkov.dev/5d1b376e86f774252519444e-icon.webp",
          "wikiLink": "https://escapefromtarkov.fandom.com/wiki/Bottle_of_Fierce_Hatchling_moonshine"
        },
        {
          "id": "5d1b385e86f774252167b98a",
          "name": "Water filter",
          "shortName": "WFilter",
          "avg24hPrice": 55065,
          "lastLowPrice": 42000,
          "changeLast48h": 1146,
          "changeLast48hPercent": 2.13,
          "updated": "2025-06-21T19:43:20.000Z",
          "sellFor": [
            {
              "source": "prapor",
              "price": 12250,
              "currency": "RUB",
              "priceRUB": 12250
            },
            {
              "source": "therapist",
              "price": 15435,
              "currency": "RUB",
              "priceRUB": 15435
            },
            {
              "source": "fence",
              "price": 9800,
              "currency": "RUB",
              "priceRUB": 9800
            },
            {
              "source": "skier",
              "price": 12005,
              "currency": "RUB",
              "priceRUB": 12005
            },
            {
              "source": "fleaMarket",
              "price": 42000,
              "currency": "RUB",
              "priceRUB": 42000
            }
          ],
          "iconLink": "https://assets.tarkov.dev/5d1b385e86f774252167b98a-icon.webp",
          "wikiLink": "https://escapefromtarkov.fandom.com/wiki/Water_filter"
        },
        {
          "id": "5d1b3a5d86f774252167ba22",
          "name": "Pile of meds",
          "shortName": "Meds",
          "avg24hPrice": 29888,
          "lastLowPrice": 25000,
          "changeLast48h": 909,
          "changeLast48hPercent": 3.14,
          "updated": "2025-06-21T19:59:37.000Z",
          "sellFor": [
            {
              "source": "therapist",
              "price": 4095,
              "currency": "RUB",
              "priceRUB": 4095
            },
            {
              "source": "fence",
              "price": 2600,
              "currency": "RUB",
              "priceRUB": 2600
            },
            {
              "source": "jaeger",
              "price": 3900,
              "currency": "RUB",
              "priceRUB": 3900
            },
            {
              "source": "fleaMarket",
              "price": 25000,
              "currency": "RUB",
              "priceRUB": 25000
            }
          ],
          "iconLink": "https://assets.tarkov.dev/5d1b3a5d86f774252167ba22-icon.webp",
          "wikiLink": "https://escapefromtarkov.fandom.com/wiki/Pile_of_meds"
        },
        {
          "id": "5d1b3f2d86f774253763b735",
          "name": "Disposable syringe",
          "shortName": "Syringe",
          "avg24hPrice": 24988,
          "lastLowPrice": 21000,
          "changeLast48h": -4582,
          "changeLast48hPercent": -15.5,
          "updated": "2025-06-21T19:12:07.000Z",
          "sellFor": [
            {
              "source": "therapist",
              "price": 5380,
              "currency": "RUB",
              "priceRUB": 5380
            },
            {
              "source": "fence",
              "price": 3416,
              "currency": "RUB",
              "priceRUB": 3416
            },
            {
              "source": "jaeger",
              "price": 5124,
              "currency": "RUB",
              "priceRUB": 5124
            },
            {
              "source": "fleaMarket",
              "price": 21000,
              "currency": "RUB",
              "priceRUB": 21000
            }
          ],
          "iconLink": "https://assets.tarkov.dev/5d1b3f2d86f774253763b735-icon.webp",
          "wikiLink": "https://escapefromtarkov.fandom.com/wiki/Disposable_syringe"
        },
        {
          "id": "5d235a5986f77443f6329bc6",
          "name": "Gold skull ring",
          "shortName": "Skull",
          "avg24hPrice": 44818,
          "lastLowPrice": 38212,
          "changeLast48h": -669,
          "changeLast48hPercent": -1.47,
          "updated": "2025-06-21T19:36:57.000Z",
          "sellFor": [
            {
              "source": "therapist",
              "price": 34650,
              "currency": "RUB",
              "priceRUB": 34650
            },
            {
              "source": "fence",
              "price": 22000,
              "currency": "RUB",
              "priceRUB": 22000
            },
            {
              "source": "skier",
              "price": 26950,
              "currency": "RUB",
              "priceRUB": 26950
            },
            {
              "source": "peacekeeper",
              "price": 210,
              "currency": "USD",
              "priceRUB": 24750
            },
            {
              "source": "fleaMarket",
              "price": 38212,
              "currency": "RUB",
              "priceRUB": 38212
            }
          ],
          "iconLink": "https://assets.tarkov.dev/5d235a5986f77443f6329bc6-icon.webp",
          "wikiLink": "https://escapefromtarkov.fandom.com/wiki/Gold_skull_ring"
        },
        {
          "id": "5d235b4d86f7742e017bc88a",
          "name": "GP coin",
          "shortName": "GP",
          "avg24hPrice": null,
          "lastLowPrice": null,
          "changeLast48h": null,
          "changeLast48hPercent": null,
          "updated": "2025-06-21T11:47:34.000Z",
          "sellFor": [],
          "iconLink": "https://assets.tarkov.dev/5d235b4d86f7742e017bc88a-icon.webp",
          "wikiLink": "https://escapefromtarkov.fandom.com/wiki/GP_coin"
        },
        {
          "id": "5d40407c86f774318526545a",
          "name": "Bottle of Tarkovskaya vodka",
          "shortName": "Vodka",
          "avg24hPrice": 30922,
          "lastLowPrice": 29999,
          "changeLast48h": -190,
          "changeLast48hPercent": -0.61,
          "updated": "2025-06-21T19:49:30.000Z",
          "sellFor": [
            {
              "source": "prapor",
              "price": 12500,
              "currency": "RUB",
              "priceRUB": 12500
            },
            {
              "source": "therapist",
              "price": 15750,
              "currency": "RUB",
              "priceRUB": 15750
            },
            {
              "source": "fence",
              "price": 10000,
              "currency": "RUB",
              "priceRUB": 10000
            },
            {
              "source": "jaeger",
              "price": 15000,
              "currency": "RUB",
              "priceRUB": 15000
            },
            {
              "source": "fleaMarket",
              "price": 29999,
              "currency": "RUB",
              "priceRUB": 29999
            }
          ],
          "iconLink": "https://assets.tarkov.dev/5d40407c86f774318526545a-icon.webp",
          "wikiLink": "https://escapefromtarkov.fandom.com/wiki/Bottle_of_Tarkovskaya_vodka"
        },
        {
          "id": "5d40412b86f7743cb332ac3a",
          "name": "Schaman shampoo",
          "shortName": "Shampoo",
          "avg24hPrice": 30609,
          "lastLowPrice": 30000,
          "changeLast48h": -1443,
          "changeLast48hPercent": -4.5,
          "updated": "2025-06-21T19:59:05.000Z",
          "sellFor": [
            {
              "source": "therapist",
              "price": 4410,
              "currency": "RUB",
              "priceRUB": 4410
            },
            {
              "source": "fence",
              "price": 2800,
              "currency": "RUB",
              "priceRUB": 2800
            },
            {
              "source": "fleaMarket",
              "price": 30000,
              "currency": "RUB",
              "priceRUB": 30000
            }
          ],
          "iconLink": "https://assets.tarkov.dev/5d40412b86f7743cb332ac3a-icon.webp",
          "wikiLink": "https://escapefromtarkov.fandom.com/wiki/Schaman_shampoo"
        },
        {
          "id": "5d6fc78386f77449d825f9dc",
          "name": "Gunpowder \"Eagle\"",
          "shortName": "Eagle",
          "avg24hPrice": 51858,
          "lastLowPrice": 50000,
          "changeLast48h": 897,
          "changeLast48hPercent": 1.76,
          "updated": "2025-06-21T19:35:49.000Z",
          "sellFor": [
            {
              "source": "prapor",
              "price": 16000,
              "currency": "RUB",
              "priceRUB": 16000
            },
            {
              "source": "therapist",
              "price": 20160,
              "currency": "RUB",
              "priceRUB": 20160
            },
            {
              "source": "fence",
              "price": 12800,
              "currency": "RUB",
              "priceRUB": 12800
            },
            {
              "source": "skier",
              "price": 15680,
              "currency": "RUB",
              "priceRUB": 15680
            },
            {
              "source": "fleaMarket",
              "price": 50000,
              "currency": "RUB",
              "priceRUB": 50000
            }
          ],
          "iconLink": "https://assets.tarkov.dev/5d6fc78386f77449d825f9dc-icon.webp",
          "wikiLink": "https://escapefromtarkov.fandom.com/wiki/Gunpowder_%22Eagle%22"
        },
        {
          "id": "5e2aedd986f7746d404f3aa4",
          "name": "GreenBat lithium battery",
          "shortName": "GreenBat",
          "avg24hPrice": 68673,
          "lastLowPrice": 61999,
          "changeLast48h": -4395,
          "changeLast48hPercent": -6.02,
          "updated": "2025-06-21T19:52:00.000Z",
          "sellFor": [
            {
              "source": "therapist",
              "price": 16380,
              "currency": "RUB",
              "priceRUB": 16380
            },
            {
              "source": "fence",
              "price": 10400,
              "currency": "RUB",
              "priceRUB": 10400
            },
            {
              "source": "peacekeeper",
              "price": 99,
              "currency": "USD",
              "priceRUB": 11700
            },
            {
              "source": "mechanic",
              "price": 14560,
              "currency": "RUB",
              "priceRUB": 14560
            },
            {
              "source": "jaeger",
              "price": 15600,
              "currency": "RUB",
              "priceRUB": 15600
            },
            {
              "source": "fleaMarket",
              "price": 61999,
              "currency": "RUB",
              "priceRUB": 61999
            }
          ],
          "iconLink": "https://assets.tarkov.dev/5e2aedd986f7746d404f3aa4-icon.webp",
          "wikiLink": "https://escapefromtarkov.fandom.com/wiki/GreenBat_lithium_battery"
        },
        {
          "id": "5e8f3423fd7471236e6e3b64",
          "name": "Bottle of Norvinsky Yadreniy premium kvass (0.6L)",
          "shortName": "Kvass",
          "avg24hPrice": 36941,
          "lastLowPrice": 36995,
          "changeLast48h": 1614,
          "changeLast48hPercent": 4.57,
          "updated": "2025-06-21T19:36:31.000Z",
          "sellFor": [
            {
              "source": "therapist",
              "price": 9785,
              "currency": "RUB",
              "priceRUB": 9785
            },
            {
              "source": "fence",
              "price": 6212,
              "currency": "RUB",
              "priceRUB": 6212
            },
            {
              "source": "jaeger",
              "price": 9319,
              "currency": "RUB",
              "priceRUB": 9319
            },
            {
              "source": "fleaMarket",
              "price": 36995,
              "currency": "RUB",
              "priceRUB": 36995
            }
          ],
          "iconLink": "https://assets.tarkov.dev/5e8f3423fd7471236e6e3b64-icon.webp",
          "wikiLink": "https://escapefromtarkov.fandom.com/wiki/Bottle_of_Norvinsky_Yadreniy_premium_kvass_(0.6L)"
        },
        {
          "id": "60391afc25aff57af81f7085",
          "name": "Ratchet wrench",
          "shortName": "Ratchet",
          "avg24hPrice": 79135,
          "lastLowPrice": 78888,
          "changeLast48h": -364,
          "changeLast48hPercent": -0.46,
          "updated": "2025-06-21T19:52:49.000Z",
          "sellFor": [
            {
              "source": "prapor",
              "price": 62000,
              "currency": "RUB",
              "priceRUB": 62000
            },
            {
              "source": "therapist",
              "price": 78120,
              "currency": "RUB",
              "priceRUB": 78120
            },
            {
              "source": "fence",
              "price": 49600,
              "currency": "RUB",
              "priceRUB": 49600
            },
            {
              "source": "mechanic",
              "price": 69440,
              "currency": "RUB",
              "priceRUB": 69440
            },
            {
              "source": "fleaMarket",
              "price": 78888,
              "currency": "RUB",
              "priceRUB": 78888
            }
          ],
          "iconLink": "https://assets.tarkov.dev/60391afc25aff57af81f7085-icon.webp",
          "wikiLink": "https://escapefromtarkov.fandom.com/wiki/Ratchet_wrench"
        },
        {
          "id": "62a0a043cf4a99369e2624a5",
          "name": "Bottle of OLOLO Multivitamins",
          "shortName": "Vitamins",
          "avg24hPrice": 20542,
          "lastLowPrice": 17420,
          "changeLast48h": -1061,
          "changeLast48hPercent": -4.91,
          "updated": "2025-06-21T19:51:18.000Z",
          "sellFor": [
            {
              "source": "therapist",
              "price": 15806,
              "currency": "RUB",
              "priceRUB": 15806
            },
            {
              "source": "fence",
              "price": 10036,
              "currency": "RUB",
              "priceRUB": 10036
            },
            {
              "source": "jaeger",
              "price": 15054,
              "currency": "RUB",
              "priceRUB": 15054
            },
            {
              "source": "fleaMarket",
              "price": 17420,
              "currency": "RUB",
              "priceRUB": 17420
            }
          ],
          "iconLink": "https://assets.tarkov.dev/62a0a043cf4a99369e2624a5-icon.webp",
          "wikiLink": "https://escapefromtarkov.fandom.com/wiki/Bottle_of_OLOLO_Multivitamins"
        },
        {
          "id": "6389c7750ef44505c87f5996",
          "name": "Microcontroller board",
          "shortName": "MB",
          "avg24hPrice": null,
          "lastLowPrice": null,
          "changeLast48h": null,
          "changeLast48hPercent": null,
          "updated": "2025-06-21T10:07:10.000Z",
          "sellFor": [
            {
              "source": "therapist",
              "price": 63000,
              "currency": "RUB",
              "priceRUB": 63000
            },
            {
              "source": "fence",
              "price": 40000,
              "currency": "RUB",
              "priceRUB": 40000
            },
            {
              "source": "skier",
              "price": 49000,
              "currency": "RUB",
              "priceRUB": 49000
            },
            {
              "source": "peacekeeper",
              "price": 381,
              "currency": "USD",
              "priceRUB": 45000
            },
            {
              "source": "mechanic",
              "price": 56000,
              "currency": "RUB",
              "priceRUB": 56000
            }
          ],
          "iconLink": "https://assets.tarkov.dev/6389c7750ef44505c87f5996-icon.webp",
          "wikiLink": "https://escapefromtarkov.fandom.com/wiki/Microcontroller_board"
        },
        {
          "id": "6389c8fb46b54c634724d847",
          "name": "Silicon Optoelectronic Integrated Circuits textbook",
          "shortName": "SOIC",
          "avg24hPrice": null,
          "lastLowPrice": null,
          "changeLast48h": null,
          "changeLast48hPercent": null,
          "updated": "2025-06-21T10:07:12.000Z",
          "sellFor": [
            {
              "source": "fence",
              "price": 200000,
              "currency": "RUB",
              "priceRUB": 200000
            },
            {
              "source": "peacekeeper",
              "price": 1907,
              "currency": "USD",
              "priceRUB": 225000
            }
          ],
          "iconLink": "https://assets.tarkov.dev/6389c8fb46b54c634724d847-icon.webp",
          "wikiLink": "https://escapefromtarkov.fandom.com/wiki/Silicon_Optoelectronic_Integrated_Circuits_textbook"
        },
        {
          "id": "6389c92d52123d5dd17f8876",
          "name": "Advanced Electronic Materials textbook",
          "shortName": "AEM",
          "avg24hPrice": null,
          "lastLowPrice": null,
          "changeLast48h": null,
          "changeLast48hPercent": null,
          "updated": "2025-06-21T10:07:14.000Z",
          "sellFor": [
            {
              "source": "fence",
              "price": 196000,
              "currency": "RUB",
              "priceRUB": 196000
            },
            {
              "source": "peacekeeper",
              "price": 1869,
              "currency": "USD",
              "priceRUB": 220500
            }
          ],
          "iconLink": "https://assets.tarkov.dev/6389c92d52123d5dd17f8876-icon.webp",
          "wikiLink": "https://escapefromtarkov.fandom.com/wiki/Advanced_Electronic_Materials_textbook"
        }
      ]
    }
  },
  "timestamp": 1750536293925,
  "expiresAt": 1750536593925
}